LICENSE
MANIFEST.in
README.md
setup.cfg
setup.py
versioneer.py
PythonAPIClientBase/APIClientBase.py
PythonAPIClientBase/LoginSession.py
PythonAPIClientBase/Mock.py
PythonAPIClientBase/VerboseLogging.py
PythonAPIClientBase/__init__.py
PythonAPIClientBase/_version.py
PythonAPIClientBase.egg-info/PKG-INFO
PythonAPIClientBase.egg-info/SOURCES.txt
PythonAPIClientBase.egg-info/dependency_links.txt
PythonAPIClientBase.egg-info/not-zip-safe
PythonAPIClientBase.egg-info/requires.txt
PythonAPIClientBase.egg-info/top_level.txt