Metadata-Version: 2.4
Name: PythonAPIClientBase
Version: 0.0.16
Summary: Base classes for APIClients
Home-page: https://github.com/rmetcalf9/PythonAPIClientBase
Author: Robert Metcalf
Author-email: rmetcalf9@googlemail.com
License: MIT
License-File: LICENSE
Requires-Dist: requests==2.31.0
Requires-Dist: pytz==2025.2
Requires-Dist: python-dateutil==2.8.1
Dynamic: author
Dynamic: author-email
Dynamic: description
Dynamic: description-content-type
Dynamic: home-page
Dynamic: license
Dynamic: license-file
Dynamic: requires-dist
Dynamic: summary
